catbase/__init__.py
catbase-1.0.0.dist-info/LICENSE.txt
catbase-1.0.0.dist-info/METADATA
catbase-1.0.0.dist-info/WHEEL
catbase-1.0.0.dist-info/top_level.txt
catbase-1.0.0.dist-info/RECORD
