Metadata-Version: 2.1
Name: catbase
Version: 1.0.0
Summary: JSON-based database you were dreaming of!
Home-page: https://github.com/milena-kos/catbase
Author: Milenakos
Author-email: business@milenakos.tk
Project-URL: Bug Tracker, https://github.com/milena-kos/catbase/issues
Project-URL: repository, https://github.com/milena-kos/catbase
Classifier: Programming Language :: Python :: 3
Classifier: License :: Public Domain
Classifier: Operating System :: OS Independent
Requires-Python: >=3.0
License-File: LICENSE.txt
